README.md
pyproject.toml
continuum_objects/__init__.py
continuum_objects/abc_continuum_object.py
continuum_objects/clusters.py
continuum_objects/continuum.py
continuum_objects/data_centers.py
continuum_objects/generic_objects.py
continuum_objects/load_json.py
continuum_objects/network.py
continuum_objects.egg-info/PKG-INFO
continuum_objects.egg-info/SOURCES.txt
continuum_objects.egg-info/dependency_links.txt
continuum_objects.egg-info/requires.txt
continuum_objects.egg-info/top_level.txt