Metadata-Version: 2.4
Name: continuum-objects
Version: 0.0.6
Summary: Python package to load, validate and export objects of the digital continuum
Requires-Python: >=3.12
Requires-Dist: pydantic>=2.12.5
